README.rst
setup.py
Chubasquero.egg-info/PKG-INFO
Chubasquero.egg-info/SOURCES.txt
Chubasquero.egg-info/dependency_links.txt
Chubasquero.egg-info/entry_points.txt
Chubasquero.egg-info/requires.txt
Chubasquero.egg-info/top_level.txt
chubasquero/__init__.py
chubasquero/core.py
chubasquero/post.py
chubasquero/static/chubasquero.css
chubasquero/static/chubasquero.js
chubasquero/static/material.css
chubasquero/static/material.js
chubasquero/static/post.js
chubasquero/static/vue.js
chubasquero/templates/index.html