Metadata-Version: 1.0
Name: Chubasquero
Version: 1.0.0
Summary: A CMS built on top of Pelican
Home-page: https://github.com/dotoscat/chubasquero
Author: Oscar (dotoscat) Triano
Author-email: UNKNOWN
License: AGPL-3.0
Platform: UNKNOWN
